[{"place_id":"celi320","geometry":{"type":"Point","coordinates":[11.213245,44.4739835]},"display_name":"Nuovo Parco dei Ciliegi","category":"eating","type":"celiachia","importance":1.0,"icon":"","visiting_time":0.0,"opening_hours":"ok","opening_days":"ok","rating":0,"photo_url":null,"description":"Glutine","www":"www.parcodeiciliegi.it"},{"place_id":"celi11147","geometry":{"type":"Point","coordinates":[11.2194481,44.4901652]},"display_name":"Sily Bar","category":"eating","type":"celiachia","importance":1.0,"icon":"","visiting_time":0.0,"opening_hours":"ok","opening_days":"ok","rating":0,"photo_url":null,"description":"Glutine","www":"www.mmglutenfree.it"},{"place_id":"celi11311","geometry":{"type":"Point","coordinates":[11.2202886,44.4907933]},"display_name":"Antica Gelateria Kapogiro","category":"eating","type":"celiachia","importance":1.0,"icon":"","visiting_time":0.0,"opening_hours":"ok","opening_days":"ok","rating":0,"photo_url":null,"description":"Glutine","www":"www.kapogiro.it"}]