[{"place_id":"44,62252890191480","geometry":{"type":"Point","coordinates":[9.332590308,44.622528902]},"display_name":"Comune di Ottone,from:IBC","category":"attractions","type":"HolderOfArchives","importance":0.0,"icon":"","visiting_time":0.0,"opening_hours":"ok","opening_days":"ok","rating":0,"photo_url":null,"description":null,"www":"http://www.comune.ottone.pc.it"},{"place_id":"44,62252890191480","geometry":{"type":"Point","coordinates":[9.332590308,44.622528902]},"display_name":"Museo Diocesano di Arte Sacra,from:IBC","category":"attractions","type":"Museum","importance":0.0,"icon":"","visiting_time":0.0,"opening_hours":"ok","opening_days":"ok","rating":0,"photo_url":null,"description":null,"www":"http://dati.emilia-romagna.it/id/ibc/condition/IT-ER-PC020"},{"place_id":"Una Farnia Monticelli d'Ongina Via Porto Pompino 220","geometry":{"type":"Point","coordinates":[9.27434449,44.6130853]},"display_name":"Una Farnia Monticelli d'Ongina Via Porto Pompino,from:IBC","category":"tree","type":"tree","importance":0.0,"icon":"","visiting_time":0.0,"opening_hours":"ok","opening_days":"ok","rating":0,"photo_url":"http://online.ibc.regione.emilia-romagna.it/mtrees/image/6656.12.06.pdf","description":null,"www":null},{"place_id":"Castagno Ottone Barchi Ovest paese 497","geometry":{"type":"Point","coordinates":[9.27434449,44.6130853]},"display_name":"Castagno Ottone Barchi Ovest paese,from:IBC","category":"tree","type":"tree","importance":0.0,"icon":"","visiting_time":0.0,"opening_hours":"ok","opening_days":"ok","rating":0,"photo_url":"http://online.ibc.regione.emilia-romagna.it/mtrees/image/955.jpg","description":null,"www":null}]