[{"place_id":"44,98773454597070","geometry":{"type":"Point","coordinates":[9.959170059,44.987734546]},"display_name":"Comune di Besenzone,from:IBC","category":"attractions","type":"HolderOfArchives","importance":0.0,"icon":"","visiting_time":0.0,"opening_hours":"ok","opening_days":"ok","rating":0,"photo_url":null,"description":null,"www":"http://www.comune.besenzone.pc.it"},{"place_id":"44,9937141","geometry":{"type":"Point","coordinates":[9.9302466,44.9937141]},"display_name":"Comune di Cortemaggiore,from:IBC","category":"attractions","type":"HolderOfArchives","importance":0.0,"icon":"","visiting_time":0.0,"opening_hours":"ok","opening_days":"ok","rating":0,"photo_url":null,"description":null,"www":"http://www.comune.cortemaggiore.pc.it"},{"place_id":"44,99459335704020","geometry":{"type":"Point","coordinates":[9.930535924,44.994593357]},"display_name":"Biblioteca comunale e Università Pallavicinia dell'età libera,from:IBC","category":"attractions","type":"Library","importance":0.0,"icon":"","visiting_time":0.0,"opening_hours":"ok","opening_days":"ok","rating":0,"photo_url":null,"description":null,"www":"http://www.comune.cortemaggiore.pc.it/index.php/biblioteca"}]