[{"place_id":"45,01210395709450","geometry":{"type":"Point","coordinates":[9.569013474,45.012103957]},"display_name":"Comune di Gragnano Trebbiense,from:IBC","category":"attractions","type":"HolderOfArchives","importance":0.0,"icon":"","visiting_time":0.0,"opening_hours":"ok","opening_days":"ok","rating":0,"photo_url":null,"description":null,"www":"http://www.comune.gragnanotrebbiense.pc.it"},{"place_id":"45,01210395709450","geometry":{"type":"Point","coordinates":[9.569013474,45.012103957]},"display_name":"Biblioteca comunale,from:IBC","category":"attractions","type":"Library","importance":0.0,"icon":"","visiting_time":0.0,"opening_hours":"ok","opening_days":"ok","rating":0,"photo_url":null,"description":null,"www":"http://dati.emilia-romagna.it/id/ibc/condition/IT-PC0017_orari"},{"place_id":"44,99684288868620","geometry":{"type":"Point","coordinates":[9.614112196,44.996842889]},"display_name":"Biblioteca comunale,from:IBC","category":"attractions","type":"Library","importance":0.0,"icon":"","visiting_time":0.0,"opening_hours":"ok","opening_days":"ok","rating":0,"photo_url":null,"description":null,"www":"http://dati.emilia-romagna.it/id/ibc/condition/IT-PC0015_orari"},{"place_id":"Farnia Gragnano Trebbiense Campremoldo Via Cascina Campagne 636","geometry":{"type":"Point","coordinates":[9.53851857,44.98520412]},"display_name":"Farnia Gragnano Trebbiense Campremoldo Via Cascina Campagne,from:IBC","category":"tree","type":"tree","importance":0.0,"icon":"","visiting_time":0.0,"opening_hours":"ok","opening_days":"ok","rating":0,"photo_url":"http://online.ibc.regione.emilia-romagna.it/mtrees/image/925.jpg","description":null,"www":null},{"place_id":"Farnia Gragnano Trebbiense Campremoldo Via Cascina Campagne 689","geometry":{"type":"Point","coordinates":[9.5447857,44.99334804]},"display_name":"Farnia Gragnano Trebbiense Campremoldo Via Cascina Campagne,from:IBC","category":"tree","type":"tree","importance":0.0,"icon":"","visiting_time":0.0,"opening_hours":"ok","opening_days":"ok","rating":0,"photo_url":"http://online.ibc.regione.emilia-romagna.it/mtrees/image/930.jpg","description":null,"www":null},{"place_id":"Farnia Gragnano Trebbiense Campremoldo Via Cascina Campagne 733","geometry":{"type":"Point","coordinates":[9.5449524,44.99353628]},"display_name":"Farnia Gragnano Trebbiense Campremoldo Via Cascina Campagne,from:IBC","category":"tree","type":"tree","importance":0.0,"icon":"","visiting_time":0.0,"opening_hours":"ok","opening_days":"ok","rating":0,"photo_url":"http://online.ibc.regione.emilia-romagna.it/mtrees/image/935.jpg","description":null,"www":null},{"place_id":"Platano Gragnano Trebbiense Caseificio Strada Agazzana 917","geometry":{"type":"Point","coordinates":[9.56696979,45.02635751]},"display_name":"Platano Gragnano Trebbiense Caseificio Strada Agazzana,from:IBC","category":"tree","type":"tree","importance":0.0,"icon":"","visiting_time":0.0,"opening_hours":"ok","opening_days":"ok","rating":0,"photo_url":"http://online.ibc.regione.emilia-romagna.it/mtrees/image/9926.jpg","description":null,"www":null}]