[{"place_id":"celi3273","geometry":{"type":"Point","coordinates":[12.5218877,43.9901115]},"display_name":"Pizz'Osteria da Mazza","category":"eating","type":"celiachia","importance":1.0,"icon":"","visiting_time":0.0,"opening_hours":"ok","opening_days":"ok","rating":0,"photo_url":null,"description":"Glutine","www":"null"},{"place_id":"celi13657","geometry":{"type":"Point","coordinates":[12.5086639,43.9846011]},"display_name":"Replay cafè","category":"eating","type":"celiachia","importance":1.0,"icon":"","visiting_time":0.0,"opening_hours":"ok","opening_days":"ok","rating":0,"photo_url":null,"description":"Glutine","www":"www.replay-cafe.com"},{"place_id":"celi13600","geometry":{"type":"Point","coordinates":[12.568355,43.982255]},"display_name":"La buona carne","category":"eating","type":"celiachia","importance":1.0,"icon":"","visiting_time":0.0,"opening_hours":"ok","opening_days":"ok","rating":0,"photo_url":null,"description":"Glutine","www":"null"}]