[{"place_id":"15040732","geometry":{"type":"Point","coordinates":[11.7479554,43.9339033]},"display_name":"Mulino Mengozzi, Strada Fiumicello Braccina, Castelletto, Premilcuore, FC, EMR, 47010, Italia","category":"attractions","type":"attraction","importance":0.001,"icon":"http://nominatim.openstreetmap.org/images/mapicons/poi_point_of_interest.p.20.png","visiting_time":30.0,"opening_hours":null,"opening_days":null,"rating":0,"photo_url":null,"description":null,"www":null},{"place_id":"5175428","geometry":{"type":"Point","coordinates":[11.8234905,43.9736733]},"display_name":"Trattoria del Cervo, 124, Via Fontana, Palazzo, Premilcuore, FC, EMR, 47010, Italia","category":"eating","type":"restaurant","importance":0.001,"icon":"http://nominatim.openstreetmap.org/images/mapicons/food_restaurant.p.20.png","visiting_time":60.0,"opening_hours":null,"opening_days":null,"rating":0,"photo_url":null,"description":null,"www":null},{"place_id":"5111922","geometry":{"type":"Point","coordinates":[11.7499961,43.9368859]},"display_name":"Fiumicello, Strada Fiumicello Braccina, Castelletto, Premilcuore, FC, EMR, 47010, Italia","category":"eating","type":"restaurant","importance":0.001,"icon":"http://nominatim.openstreetmap.org/images/mapicons/food_restaurant.p.20.png","visiting_time":60.0,"opening_hours":null,"opening_days":null,"rating":0,"photo_url":null,"description":null,"www":null},{"place_id":"63277183","geometry":{"type":"Point","coordinates":[11.7863122,43.9043368]},"display_name":"Ristorante Bar, Strada Provinciale 4 del Bidente, San Giovanni, Santa Sofia, FC, EMR, 47010, Italia","category":"eating","type":"restaurant","importance":0.001,"icon":"http://nominatim.openstreetmap.org/images/mapicons/food_restaurant.p.20.png","visiting_time":60.0,"opening_hours":null,"opening_days":null,"rating":0,"photo_url":null,"description":null,"www":null},{"place_id":"5175428","geometry":{"type":"Point","coordinates":[11.8234905,43.9736733]},"display_name":"Trattoria del Cervo, 124, Via Fontana, Palazzo, Premilcuore, FC, EMR, 47010, Italia","category":"eating","type":"restaurant","importance":0.001,"icon":"http://nominatim.openstreetmap.org/images/mapicons/food_restaurant.p.20.png","visiting_time":60.0,"opening_hours":null,"opening_days":null,"rating":0,"photo_url":null,"description":null,"www":null},{"place_id":"5111922","geometry":{"type":"Point","coordinates":[11.7499961,43.9368859]},"display_name":"Fiumicello, Strada Fiumicello Braccina, Castelletto, Premilcuore, FC, EMR, 47010, Italia","category":"eating","type":"restaurant","importance":0.001,"icon":"http://nominatim.openstreetmap.org/images/mapicons/food_restaurant.p.20.png","visiting_time":60.0,"opening_hours":null,"opening_days":null,"rating":0,"photo_url":null,"description":null,"www":null},{"place_id":"63277183","geometry":{"type":"Point","coordinates":[11.7863122,43.9043368]},"display_name":"Ristorante Bar, Strada Provinciale 4 del Bidente, San Giovanni, Santa Sofia, FC, EMR, 47010, Italia","category":"eating","type":"restaurant","importance":0.001,"icon":"http://nominatim.openstreetmap.org/images/mapicons/food_restaurant.p.20.png","visiting_time":60.0,"opening_hours":null,"opening_days":null,"rating":0,"photo_url":null,"description":null,"www":null},{"place_id":"19494028","geometry":{"type":"Point","coordinates":[11.8698072,44.0136637]},"display_name":"Torre di Monte Erno, Via San Zenone, Busco, Galeata, FC, EMR, 47017, Italia","category":"attractions","type":"castle","importance":0.001,"icon":"http://nominatim.openstreetmap.org/images/mapicons/tourist_castle.p.20.png","visiting_time":120.0,"opening_hours":null,"opening_days":null,"rating":0,"photo_url":null,"description":null,"www":null},{"place_id":"4861869","geometry":{"type":"Point","coordinates":[11.8190725,43.9641737]},"display_name":"Torre di Montalto, CAI 331 - Tiravento Torre Montalto, Castellare, Premilcuore, FC, EMR, 47010, Italia","category":"attractions","type":"ruins","importance":0.001,"icon":"http://nominatim.openstreetmap.org/images/mapicons/tourist_ruin.p.20.png","visiting_time":30.0,"opening_hours":null,"opening_days":null,"rating":0,"photo_url":null,"description":null,"www":null},{"place_id":"7087154","geometry":{"type":"Point","coordinates":[11.8292473,44.0077038]},"display_name":"Torre Di Montalto (rudere), Strada Provinciale 3 del Rabbi, Cantina di Sotto, Premilcuore, FC, EMR, 47017, Italia","category":"attractions","type":"ruins","importance":0.001,"icon":"http://nominatim.openstreetmap.org/images/mapicons/tourist_ruin.p.20.png","visiting_time":30.0,"opening_hours":null,"opening_days":null,"rating":0,"photo_url":null,"description":null,"www":null},{"place_id":"59658081","geometry":{"type":"Point","coordinates":[11.7786395,43.9030759]},"display_name":"Castellaccio di Corniolino, Granducale vecchia, Faltroncella, Santa Sofia, FC, EMR, 47018, Italia","category":"attractions","type":"ruins","importance":0.001,"icon":"http://nominatim.openstreetmap.org/images/mapicons/tourist_ruin.p.20.png","visiting_time":30.0,"opening_hours":null,"opening_days":null,"rating":0,"photo_url":null,"description":null,"www":null},{"place_id":"112231393","geometry":{"type":"Point","coordinates":[11.773389501,43.97391255]},"display_name":"SP3 del Rabbi, Le Piane, Valstavole, Premilcuore, FC, EMR, 47010, Italia","category":"lifestyle","type":"bar","importance":0.001,"icon":"http://nominatim.openstreetmap.org/images/mapicons/food_bar.p.20.png","visiting_time":10.0,"opening_hours":null,"opening_days":null,"rating":0,"photo_url":null,"description":null,"www":null},{"place_id":"20335213","geometry":{"type":"Point","coordinates":[11.7812505,44.0255781]},"display_name":"Toscoromagnola, Portico e San Benedetto, Moreta, Portico e San Benedetto, FC, EMR, Italia","category":"lifestyle","type":"bar","importance":0.001,"icon":"http://nominatim.openstreetmap.org/images/mapicons/food_bar.p.20.png","visiting_time":10.0,"opening_hours":null,"opening_days":null,"rating":0,"photo_url":null,"description":null,"www":null},{"place_id":"112231393","geometry":{"type":"Point","coordinates":[11.773389501,43.97391255]},"display_name":"SP3 del Rabbi, Le Piane, Valstavole, Premilcuore, FC, EMR, 47010, Italia","category":"lifestyle","type":"bar","importance":0.001,"icon":"http://nominatim.openstreetmap.org/images/mapicons/food_bar.p.20.png","visiting_time":90.0,"opening_hours":null,"opening_days":null,"rating":0,"photo_url":null,"description":null,"www":null},{"place_id":"20335213","geometry":{"type":"Point","coordinates":[11.7812505,44.0255781]},"display_name":"Toscoromagnola, Portico e San Benedetto, Moreta, Portico e San Benedetto, FC, EMR, Italia","category":"lifestyle","type":"bar","importance":0.001,"icon":"http://nominatim.openstreetmap.org/images/mapicons/food_bar.p.20.png","visiting_time":90.0,"opening_hours":null,"opening_days":null,"rating":0,"photo_url":null,"description":null,"www":null},{"place_id":"180169053","geometry":{"type":"Point","coordinates":[-8.3350726,43.2233149]},"display_name":"Abegondo, Galicia, CAFE, España","category":"lifestyle","type":"postcode","importance":0.2125,"icon":null,"visiting_time":10.0,"opening_hours":null,"opening_days":null,"rating":0,"photo_url":null,"description":null,"www":null},{"place_id":"7199307","geometry":{"type":"Point","coordinates":[11.8373662,44.0103486]},"display_name":"Strada Provinciale 3 del Rabbi, Cantina di Sotto, Premilcuore, FC, EMR, 47017, Italia","category":"attractions","type":"memorial","importance":0.001,"icon":"http://nominatim.openstreetmap.org/images/mapicons/tourist_monument.p.20.png","visiting_time":10.0,"opening_hours":null,"opening_days":null,"rating":0,"photo_url":null,"description":null,"www":null},{"place_id":"7605962","geometry":{"type":"Point","coordinates":[11.8382459,43.9056296]},"display_name":"Cippo ai Partigiani, Biserno - San Paolo in Alpe, Collina, Santa Sofia, FC, EMR, 47010, Italia","category":"attractions","type":"memorial","importance":0.001,"icon":"http://nominatim.openstreetmap.org/images/mapicons/tourist_monument.p.20.png","visiting_time":10.0,"opening_hours":null,"opening_days":null,"rating":0,"photo_url":null,"description":null,"www":null},{"place_id":"22933801","geometry":{"type":"Point","coordinates":[11.8142503,43.9241482]},"display_name":"Cippo ai Partigiani, Strada per Badia di Sasso, Campone, Santa Sofia, FC, EMR, 47010, Italia","category":"attractions","type":"memorial","importance":0.001,"icon":"http://nominatim.openstreetmap.org/images/mapicons/tourist_monument.p.20.png","visiting_time":10.0,"opening_hours":null,"opening_days":null,"rating":0,"photo_url":null,"description":null,"www":null},{"place_id":"7199307","geometry":{"type":"Point","coordinates":[11.8373662,44.0103486]},"display_name":"Strada Provinciale 3 del Rabbi, Cantina di Sotto, Premilcuore, FC, EMR, 47017, Italia","category":"attractions","type":"memorial","importance":0.001,"icon":"http://nominatim.openstreetmap.org/images/mapicons/tourist_monument.p.20.png","visiting_time":10.0,"opening_hours":null,"opening_days":null,"rating":0,"photo_url":null,"description":null,"www":null},{"place_id":"22933801","geometry":{"type":"Point","coordinates":[11.8142503,43.9241482]},"display_name":"Cippo ai Partigiani, Strada per Badia di Sasso, Campone, Santa Sofia, FC, EMR, 47010, Italia","category":"attractions","type":"memorial","importance":0.001,"icon":"http://nominatim.openstreetmap.org/images/mapicons/tourist_monument.p.20.png","visiting_time":10.0,"opening_hours":null,"opening_days":null,"rating":0,"photo_url":null,"description":null,"www":null},{"place_id":"7605962","geometry":{"type":"Point","coordinates":[11.8382459,43.9056296]},"display_name":"Cippo ai Partigiani, Biserno - San Paolo in Alpe, Collina, Santa Sofia, FC, EMR, 47010, Italia","category":"attractions","type":"memorial","importance":0.001,"icon":"http://nominatim.openstreetmap.org/images/mapicons/tourist_monument.p.20.png","visiting_time":10.0,"opening_hours":null,"opening_days":null,"rating":0,"photo_url":null,"description":null,"www":null},{"place_id":"56302213","geometry":{"type":"Point","coordinates":[11.6878462,43.9815777]},"display_name":"SP55, Casetta, Portico e San Benedetto, FC, EMR, Italia","category":"attractions","type":"monument","importance":0.001,"icon":"http://nominatim.openstreetmap.org/images/mapicons/tourist_monument.p.20.png","visiting_time":10.0,"opening_hours":null,"opening_days":null,"rating":0,"photo_url":null,"description":null,"www":null},{"place_id":"165049261","geometry":{"type":"Point","coordinates":[11.68922234,43.9822572]},"display_name":"Casetta, Portico e San Benedetto, FC, EMR, Italia","category":"parks","type":"park","importance":0.15,"icon":null,"visiting_time":90.0,"opening_hours":null,"opening_days":null,"rating":0,"photo_url":null,"description":null,"www":null},{"place_id":"172637434","geometry":{"type":"Point","coordinates":[11.782237414,44.02564925]},"display_name":"Giardini pubblici, Portico e San Benedetto, Canova, Portico e San Benedetto, FC, EMR, Italia","category":"parks","type":"park","importance":0.15,"icon":null,"visiting_time":90.0,"opening_hours":null,"opening_days":null,"rating":0,"photo_url":null,"description":null,"www":null},{"place_id":"112689105","geometry":{"type":"Point","coordinates":[11.864110856,43.9481748]},"display_name":"Cappella, CAI 271, Castello di Spescia, Santa Sofia, FC, EMR, Italia","category":"attractions","type":"place_of_worship","importance":0.101,"icon":"http://nominatim.openstreetmap.org/images/mapicons/place_of_worship_unknown3.p.20.png","visiting_time":30.0,"opening_hours":null,"opening_days":null,"rating":0,"photo_url":null,"description":null,"www":null},{"place_id":"108268800","geometry":{"type":"Point","coordinates":[11.79530387,43.9071618]},"display_name":"Strada Fiumicello Braccina, Valdonasso di Sotto, Santa Sofia, FC, EMR, 47010, Italia","category":"attractions","type":"place_of_worship","importance":0.101,"icon":"http://nominatim.openstreetmap.org/images/mapicons/place_of_worship_unknown3.p.20.png","visiting_time":30.0,"opening_hours":null,"opening_days":null,"rating":0,"photo_url":null,"description":null,"www":null},{"place_id":"165117295","geometry":{"type":"Point","coordinates":[11.8469426,43.90368325]},"display_name":"Isola - Ridracoli, Ca' d'Achille, Santa Sofia, FC, EMR, Italia","category":"attractions","type":"place_of_worship","importance":0.101,"icon":"http://nominatim.openstreetmap.org/images/mapicons/place_of_worship_unknown3.p.20.png","visiting_time":30.0,"opening_hours":null,"opening_days":null,"rating":0,"photo_url":null,"description":null,"www":null},{"place_id":"113125980","geometry":{"type":"Point","coordinates":[11.783115642,43.9800995]},"display_name":"Chiesa di Santa Maria delle Nevi, SP3 del Rabbi, Le Piane, Valstavole, Premilcuore, FC, EMR, 47010, Italia","category":"attractions","type":"place_of_worship","importance":0.001,"icon":"http://nominatim.openstreetmap.org/images/mapicons/place_of_worship_unknown3.p.20.png","visiting_time":30.0,"opening_hours":null,"opening_days":null,"rating":0,"photo_url":null,"description":null,"www":null},{"place_id":"84519126","geometry":{"type":"Point","coordinates":[11.843746209,44.01352985]},"display_name":"Pieve di Fantella, Strada Provinciale 3 del Rabbi, Cantina di Sotto, Premilcuore, FC, EMR, 47017, Italia","category":"attractions","type":"place_of_worship","importance":0.001,"icon":"http://nominatim.openstreetmap.org/images/mapicons/place_of_worship_unknown3.p.20.png","visiting_time":30.0,"opening_hours":null,"opening_days":null,"rating":0,"photo_url":null,"description":null,"www":null},{"place_id":"112730539","geometry":{"type":"Point","coordinates":[11.82585425,43.97295505]},"display_name":"Parrocchia di Sant'Agata, Via padre pietro leoni, Montaletto, Premilcuore, FC, EMR, 47010, Italia","category":"attractions","type":"place_of_worship","importance":0.001,"icon":"http://nominatim.openstreetmap.org/images/mapicons/place_of_worship_unknown3.p.20.png","visiting_time":30.0,"opening_hours":null,"opening_days":null,"rating":0,"photo_url":null,"description":null,"www":null},{"place_id":"112760661","geometry":{"type":"Point","coordinates":[11.843870237,44.01355325]},"display_name":"Strada Provinciale 3 del Rabbi, Cantina di Sotto, Premilcuore, FC, EMR, 47017, Italia","category":"attractions","type":"place_of_worship","importance":0.001,"icon":"http://nominatim.openstreetmap.org/images/mapicons/place_of_worship_unknown3.p.20.png","visiting_time":30.0,"opening_hours":null,"opening_days":null,"rating":0,"photo_url":null,"description":null,"www":null},{"place_id":"114804693","geometry":{"type":"Point","coordinates":[11.782718982,44.0252546]},"display_name":"Chiesa della Compagnia, Via Roma, Portico e San Benedetto, Canova, Portico e San Benedetto, FC, EMR, Italia","category":"attractions","type":"place_of_worship","importance":0.001,"icon":"http://nominatim.openstreetmap.org/images/mapicons/place_of_worship_unknown3.p.20.png","visiting_time":30.0,"opening_hours":null,"opening_days":null,"rating":0,"photo_url":null,"description":null,"www":null},{"place_id":"113260618","geometry":{"type":"Point","coordinates":[11.782735947,44.02566565]},"display_name":"Chiesa di Portico di Romagna, Toscoromagnola, Portico e San Benedetto, Moreta, Portico e San Benedetto, FC, EMR, Italia","category":"attractions","type":"place_of_worship","importance":0.001,"icon":"http://nominatim.openstreetmap.org/images/mapicons/place_of_worship_unknown3.p.20.png","visiting_time":30.0,"opening_hours":null,"opening_days":null,"rating":0,"photo_url":null,"description":null,"www":null},{"place_id":"113125980","geometry":{"type":"Point","coordinates":[11.783115642,43.9800995]},"display_name":"Chiesa di Santa Maria delle Nevi, SP3 del Rabbi, Le Piane, Valstavole, Premilcuore, FC, EMR, 47010, Italia","category":"attractions","type":"place_of_worship","importance":0.001,"icon":"http://nominatim.openstreetmap.org/images/mapicons/place_of_worship_unknown3.p.20.png","visiting_time":30.0,"opening_hours":null,"opening_days":null,"rating":0,"photo_url":null,"description":null,"www":null},{"place_id":"84519126","geometry":{"type":"Point","coordinates":[11.843746209,44.01352985]},"display_name":"Pieve di Fantella, Strada Provinciale 3 del Rabbi, Cantina di Sotto, Premilcuore, FC, EMR, 47017, Italia","category":"attractions","type":"place_of_worship","importance":0.001,"icon":"http://nominatim.openstreetmap.org/images/mapicons/place_of_worship_unknown3.p.20.png","visiting_time":30.0,"opening_hours":null,"opening_days":null,"rating":0,"photo_url":null,"description":null,"www":null},{"place_id":"112730539","geometry":{"type":"Point","coordinates":[11.82585425,43.97295505]},"display_name":"Parrocchia di Sant'Agata, Via padre pietro leoni, Montaletto, Premilcuore, FC, EMR, 47010, Italia","category":"attractions","type":"place_of_worship","importance":0.001,"icon":"http://nominatim.openstreetmap.org/images/mapicons/place_of_worship_unknown3.p.20.png","visiting_time":30.0,"opening_hours":null,"opening_days":null,"rating":0,"photo_url":null,"description":null,"www":null},{"place_id":"112760661","geometry":{"type":"Point","coordinates":[11.843870237,44.01355325]},"display_name":"Strada Provinciale 3 del Rabbi, Cantina di Sotto, Premilcuore, FC, EMR, 47017, Italia","category":"attractions","type":"place_of_worship","importance":0.001,"icon":"http://nominatim.openstreetmap.org/images/mapicons/place_of_worship_unknown3.p.20.png","visiting_time":30.0,"opening_hours":null,"opening_days":null,"rating":0,"photo_url":null,"description":null,"www":null},{"place_id":"108268800","geometry":{"type":"Point","coordinates":[11.79530387,43.9071618]},"display_name":"Strada Fiumicello Braccina, Valdonasso di Sotto, Santa Sofia, FC, EMR, 47010, Italia","category":"attractions","type":"place_of_worship","importance":0.001,"icon":"http://nominatim.openstreetmap.org/images/mapicons/place_of_worship_unknown3.p.20.png","visiting_time":30.0,"opening_hours":null,"opening_days":null,"rating":0,"photo_url":null,"description":null,"www":null},{"place_id":"112689105","geometry":{"type":"Point","coordinates":[11.864110856,43.9481748]},"display_name":"Cappella, CAI 271, Castello di Spescia, Santa Sofia, FC, EMR, Italia","category":"attractions","type":"place_of_worship","importance":0.001,"icon":"http://nominatim.openstreetmap.org/images/mapicons/place_of_worship_unknown3.p.20.png","visiting_time":30.0,"opening_hours":null,"opening_days":null,"rating":0,"photo_url":null,"description":null,"www":null},{"place_id":"165117295","geometry":{"type":"Point","coordinates":[11.8469426,43.90368325]},"display_name":"Isola - Ridracoli, Ca' d'Achille, Santa Sofia, FC, EMR, Italia","category":"attractions","type":"place_of_worship","importance":0.001,"icon":"http://nominatim.openstreetmap.org/images/mapicons/place_of_worship_unknown3.p.20.png","visiting_time":30.0,"opening_hours":null,"opening_days":null,"rating":0,"photo_url":null,"description":null,"www":null},{"place_id":"114804693","geometry":{"type":"Point","coordinates":[11.782718982,44.0252546]},"display_name":"Chiesa della Compagnia, Via Roma, Portico e San Benedetto, Canova, Portico e San Benedetto, FC, EMR, Italia","category":"attractions","type":"place_of_worship","importance":0.001,"icon":"http://nominatim.openstreetmap.org/images/mapicons/place_of_worship_unknown3.p.20.png","visiting_time":30.0,"opening_hours":null,"opening_days":null,"rating":0,"photo_url":null,"description":null,"www":null},{"place_id":"113260618","geometry":{"type":"Point","coordinates":[11.782735947,44.02566565]},"display_name":"Chiesa di Portico di Romagna, Toscoromagnola, Portico e San Benedetto, Moreta, Portico e San Benedetto, FC, EMR, Italia","category":"attractions","type":"place_of_worship","importance":0.001,"icon":"http://nominatim.openstreetmap.org/images/mapicons/place_of_worship_unknown3.p.20.png","visiting_time":30.0,"opening_hours":null,"opening_days":null,"rating":0,"photo_url":null,"description":null,"www":null},{"place_id":"60609621","geometry":{"type":"Point","coordinates":[11.7822557,44.0253691]},"display_name":"Hotel e ristorante La Canonica, Via Roma, Portico e San Benedetto, Canova, Portico e San Benedetto, FC, EMR, Italia","category":"resting","type":"hotel","importance":0.101,"icon":"http://nominatim.openstreetmap.org/images/mapicons/accommodation_hotel2.p.20.png","visiting_time":10.0,"opening_hours":null,"opening_days":null,"rating":0,"photo_url":null,"description":null,"www":null},{"place_id":"7883977","geometry":{"type":"Point","coordinates":[11.7888819,43.9169639]},"display_name":"Camping Vivaio, Strada Fiumicello Braccina, Valdonasso di Sotto, Santa Sofia, FC, EMR, 47010, Italia","category":"resting","type":"camp_site","importance":0.101,"icon":null,"visiting_time":10.0,"opening_hours":null,"opening_days":null,"rating":0,"photo_url":null,"description":null,"www":null},{"place_id":"4006858","geometry":{"type":"Point","coordinates":[11.686194,43.9827491]},"display_name":"Campeggio Acquacheta, Via Acquacheta, Caprile, Portico e San Benedetto, FC, EMR, Italia","category":"resting","type":"camp_site","importance":0.101,"icon":null,"visiting_time":10.0,"opening_hours":null,"opening_days":null,"rating":0,"photo_url":null,"description":null,"www":null},{"place_id":"170710010","geometry":{"type":"Point","coordinates":[11.772901035,43.97400295]},"display_name":"SP3 del Rabbi, Le Piane, Valstavole, Premilcuore, FC, EMR, 47010, Italia","category":"resting","type":"camp_site","importance":0.001,"icon":null,"visiting_time":10.0,"opening_hours":null,"opening_days":null,"rating":0,"photo_url":null,"description":null,"www":null}]