[{"place_id":"53372885","geometry":{"type":"Point","coordinates":[9.4368776,44.8340284]},"display_name":"Costa Filietto, SP65, C. Il Poggio, Piozzano, PC, EMR, Italia","category":"eating","type":"restaurant","importance":0.001,"icon":"http://nominatim.openstreetmap.org/images/mapicons/food_restaurant.p.20.png","visiting_time":60.0,"opening_hours":null,"opening_days":null,"rating":0,"photo_url":null,"description":null,"www":null},{"place_id":"53372885","geometry":{"type":"Point","coordinates":[9.4368776,44.8340284]},"display_name":"Costa Filietto, SP65, C. Il Poggio, Piozzano, PC, EMR, Italia","category":"eating","type":"restaurant","importance":0.001,"icon":"http://nominatim.openstreetmap.org/images/mapicons/food_restaurant.p.20.png","visiting_time":60.0,"opening_hours":null,"opening_days":null,"rating":0,"photo_url":null,"description":null,"www":null},{"place_id":"13278169","geometry":{"type":"Point","coordinates":[9.3927053,44.9142112]},"display_name":"Rocca d'Olgisio, Strada comunale Pecorara, Pecorara, PC, EMR, Italia","category":"attractions","type":"castle","importance":0.1667999,"icon":"http://nominatim.openstreetmap.org/images/mapicons/tourist_castle.p.20.png","visiting_time":120.0,"opening_hours":null,"opening_days":null,"rating":0,"photo_url":null,"description":null,"www":null},{"place_id":"151002988","geometry":{"type":"Point","coordinates":[9.329285046,44.8379455]},"display_name":"Castello di Romagnese, Via Roma, Canevizza, Romagnese, PV, LOM, Italia","category":"attractions","type":"castle","importance":0.001,"icon":"http://nominatim.openstreetmap.org/images/mapicons/tourist_castle.p.20.png","visiting_time":120.0,"opening_hours":null,"opening_days":null,"rating":0,"photo_url":null,"description":null,"www":null},{"place_id":"152902642","geometry":{"type":"Point","coordinates":[9.327283132,44.83727465]},"display_name":"Via Zavattarello, Canevizza, Romagnese, PV, LOM, Italia","category":"lifestyle","type":"bar","importance":0.001,"icon":"http://nominatim.openstreetmap.org/images/mapicons/food_bar.p.20.png","visiting_time":10.0,"opening_hours":null,"opening_days":null,"rating":0,"photo_url":null,"description":null,"www":null},{"place_id":"150394258","geometry":{"type":"Point","coordinates":[9.328597713,44.8378016]},"display_name":"Piazza Castello, Canevizza, Romagnese, PV, LOM, Italia","category":"lifestyle","type":"bar","importance":0.001,"icon":"http://nominatim.openstreetmap.org/images/mapicons/food_bar.p.20.png","visiting_time":10.0,"opening_hours":null,"opening_days":null,"rating":0,"photo_url":null,"description":null,"www":null},{"place_id":"47891777","geometry":{"type":"Point","coordinates":[9.3290459,44.9044951]},"display_name":"Via Manin, Frascati, Nibbiano, PC, EMR, Italia","category":"lifestyle","type":"bar","importance":0.001,"icon":"http://nominatim.openstreetmap.org/images/mapicons/food_bar.p.20.png","visiting_time":10.0,"opening_hours":null,"opening_days":null,"rating":0,"photo_url":null,"description":null,"www":null},{"place_id":"58456730","geometry":{"type":"Point","coordinates":[9.3867173,44.8575294]},"display_name":"Arcobaleno, SP34, Pecorara, PC, EMR, 29022, Italia","category":"lifestyle","type":"bar","importance":0.001,"icon":"http://nominatim.openstreetmap.org/images/mapicons/food_bar.p.20.png","visiting_time":10.0,"opening_hours":null,"opening_days":null,"rating":0,"photo_url":null,"description":null,"www":null},{"place_id":"152902642","geometry":{"type":"Point","coordinates":[9.327283132,44.83727465]},"display_name":"Via Zavattarello, Canevizza, Romagnese, PV, LOM, Italia","category":"lifestyle","type":"bar","importance":0.001,"icon":"http://nominatim.openstreetmap.org/images/mapicons/food_bar.p.20.png","visiting_time":90.0,"opening_hours":null,"opening_days":null,"rating":0,"photo_url":null,"description":null,"www":null},{"place_id":"150394258","geometry":{"type":"Point","coordinates":[9.328597713,44.8378016]},"display_name":"Piazza Castello, Canevizza, Romagnese, PV, LOM, Italia","category":"lifestyle","type":"bar","importance":0.001,"icon":"http://nominatim.openstreetmap.org/images/mapicons/food_bar.p.20.png","visiting_time":90.0,"opening_hours":null,"opening_days":null,"rating":0,"photo_url":null,"description":null,"www":null},{"place_id":"47891777","geometry":{"type":"Point","coordinates":[9.3290459,44.9044951]},"display_name":"Via Manin, Frascati, Nibbiano, PC, EMR, Italia","category":"lifestyle","type":"bar","importance":0.001,"icon":"http://nominatim.openstreetmap.org/images/mapicons/food_bar.p.20.png","visiting_time":90.0,"opening_hours":null,"opening_days":null,"rating":0,"photo_url":null,"description":null,"www":null},{"place_id":"58456730","geometry":{"type":"Point","coordinates":[9.3867173,44.8575294]},"display_name":"Arcobaleno, SP34, Pecorara, PC, EMR, 29022, Italia","category":"lifestyle","type":"bar","importance":0.001,"icon":"http://nominatim.openstreetmap.org/images/mapicons/food_bar.p.20.png","visiting_time":90.0,"opening_hours":null,"opening_days":null,"rating":0,"photo_url":null,"description":null,"www":null},{"place_id":"180169053","geometry":{"type":"Point","coordinates":[-8.3350726,43.2233149]},"display_name":"Abegondo, Galicia, CAFE, España","category":"lifestyle","type":"postcode","importance":0.2125,"icon":null,"visiting_time":10.0,"opening_hours":null,"opening_days":null,"rating":0,"photo_url":null,"description":null,"www":null},{"place_id":"60429225","geometry":{"type":"Point","coordinates":[9.3291137,44.8380787]},"display_name":"Monumento ai caduti, Via Roma, Canevizza, Romagnese, PV, LOM, Italia","category":"attractions","type":"monument","importance":0.101,"icon":"http://nominatim.openstreetmap.org/images/mapicons/tourist_monument.p.20.png","visiting_time":10.0,"opening_hours":null,"opening_days":null,"rating":0,"photo_url":null,"description":null,"www":null},{"place_id":"56327866","geometry":{"type":"Point","coordinates":[9.3893345,44.8543742]},"display_name":"Monumento agli Alpini, SP34, Pecorara, PC, EMR, 29022, Italia","category":"attractions","type":"monument","importance":0.101,"icon":"http://nominatim.openstreetmap.org/images/mapicons/tourist_monument.p.20.png","visiting_time":10.0,"opening_hours":null,"opening_days":null,"rating":0,"photo_url":null,"description":null,"www":null},{"place_id":"56899477","geometry":{"type":"Point","coordinates":[9.3927368,44.8560146]},"display_name":"Targa ai caduti, La Bulèra (M.te Lazzaro), Pecorara, PC, EMR, Italia","category":"attractions","type":"monument","importance":0.001,"icon":"http://nominatim.openstreetmap.org/images/mapicons/tourist_monument.p.20.png","visiting_time":10.0,"opening_hours":null,"opening_days":null,"rating":0,"photo_url":null,"description":null,"www":null},{"place_id":"153236290","geometry":{"type":"Point","coordinates":[9.331399704,44.8402656]},"display_name":"Canevizza, Romagnese, PV, LOM, Italia","category":"parks","type":"park","importance":0.15,"icon":null,"visiting_time":90.0,"opening_hours":null,"opening_days":null,"rating":0,"photo_url":null,"description":null,"www":null},{"place_id":"153862579","geometry":{"type":"Point","coordinates":[9.316554951,44.8671951]},"display_name":"Ca' Bozzi, Romagnese, PV, LOM, Italia","category":"parks","type":"park","importance":0.15,"icon":null,"visiting_time":90.0,"opening_hours":null,"opening_days":null,"rating":0,"photo_url":null,"description":null,"www":null},{"place_id":"17297792","geometry":{"type":"Point","coordinates":[9.3207367,44.8816438]},"display_name":"Parchi di studio e riflessione / Casa Giorgi, Pecorara, PC, EMR, Italia","category":"parks","type":"park","importance":0.15,"icon":null,"visiting_time":90.0,"opening_hours":null,"opening_days":null,"rating":0,"photo_url":null,"description":null,"www":null},{"place_id":"50301605","geometry":{"type":"Point","coordinates":[9.322423,44.8521612]},"display_name":"Oratorio della Beata Vergine delle Grazie, Località Ossio, Molino, Romagnese, PV, LOM, Italia","category":"attractions","type":"place_of_worship","importance":0.001,"icon":"http://nominatim.openstreetmap.org/images/mapicons/place_of_worship_unknown3.p.20.png","visiting_time":30.0,"opening_hours":null,"opening_days":null,"rating":0,"photo_url":null,"description":null,"www":null},{"place_id":"49037087","geometry":{"type":"Point","coordinates":[9.3158979,44.8348291]},"display_name":"Oratorio di San Rocco, Frazione Ariore Villa, Canevizza, Romagnese, PV, LOM, Italia","category":"attractions","type":"place_of_worship","importance":0.001,"icon":"http://nominatim.openstreetmap.org/images/mapicons/place_of_worship_unknown3.p.20.png","visiting_time":30.0,"opening_hours":null,"opening_days":null,"rating":0,"photo_url":null,"description":null,"www":null},{"place_id":"150270717","geometry":{"type":"Point","coordinates":[9.327067088,44.83788045]},"display_name":"Chiesa di San Lorenzo, Piazza Castello, Canevizza, Romagnese, PV, LOM, Italia","category":"attractions","type":"place_of_worship","importance":0.001,"icon":"http://nominatim.openstreetmap.org/images/mapicons/place_of_worship_unknown3.p.20.png","visiting_time":30.0,"opening_hours":null,"opening_days":null,"rating":0,"photo_url":null,"description":null,"www":null},{"place_id":"153339363","geometry":{"type":"Point","coordinates":[9.329408653,44.8410941]},"display_name":"SPexSS412, Molino, Romagnese, PV, LOM, Italia","category":"attractions","type":"place_of_worship","importance":0.001,"icon":"http://nominatim.openstreetmap.org/images/mapicons/place_of_worship_unknown3.p.20.png","visiting_time":30.0,"opening_hours":null,"opening_days":null,"rating":0,"photo_url":null,"description":null,"www":null},{"place_id":"48954706","geometry":{"type":"Point","coordinates":[9.3456213,44.8340537]},"display_name":"Oratorio di Maria Ausiliatrice, 219 - 19, Ca' Casarini, Romagnese, PC, LOM, Italia","category":"attractions","type":"place_of_worship","importance":0.001,"icon":"http://nominatim.openstreetmap.org/images/mapicons/place_of_worship_unknown3.p.20.png","visiting_time":30.0,"opening_hours":null,"opening_days":null,"rating":0,"photo_url":null,"description":null,"www":null},{"place_id":"150471633","geometry":{"type":"Point","coordinates":[9.33245525,44.8372237]},"display_name":"Chiesetta ai Morti di San Lorenzo, SPexSS412, Canevizza, Romagnese, PV, LOM, Italia","category":"attractions","type":"place_of_worship","importance":0.001,"icon":"http://nominatim.openstreetmap.org/images/mapicons/place_of_worship_unknown3.p.20.png","visiting_time":30.0,"opening_hours":null,"opening_days":null,"rating":0,"photo_url":null,"description":null,"www":null},{"place_id":"50251535","geometry":{"type":"Point","coordinates":[9.3364492,44.8435103]},"display_name":"Oratorio di Nostra Signora di Loreto, Via Castana, Canevizza, Romagnese, PV, LOM, Italia","category":"attractions","type":"place_of_worship","importance":0.001,"icon":"http://nominatim.openstreetmap.org/images/mapicons/place_of_worship_unknown3.p.20.png","visiting_time":30.0,"opening_hours":null,"opening_days":null,"rating":0,"photo_url":null,"description":null,"www":null},{"place_id":"162463207","geometry":{"type":"Point","coordinates":[9.441318807,44.84668655]},"display_name":"SP65, C. Il Poggio, Piozzano, PC, EMR, Italia","category":"attractions","type":"place_of_worship","importance":0.001,"icon":"http://nominatim.openstreetmap.org/images/mapicons/place_of_worship_unknown3.p.20.png","visiting_time":30.0,"opening_hours":null,"opening_days":null,"rating":0,"photo_url":null,"description":null,"www":null},{"place_id":"114452371","geometry":{"type":"Point","coordinates":[9.448557616,44.90807735]},"display_name":"Chiesa di San Nazaro e Celso, SP65, C. Il Poggio, Piozzano, PC, EMR, Italia","category":"attractions","type":"place_of_worship","importance":0.001,"icon":"http://nominatim.openstreetmap.org/images/mapicons/place_of_worship_unknown3.p.20.png","visiting_time":30.0,"opening_hours":null,"opening_days":null,"rating":0,"photo_url":null,"description":null,"www":null},{"place_id":"12364434","geometry":{"type":"Point","coordinates":[9.4106243,44.905327]},"display_name":"Strada Chiarone, Ca Nuova Gazzoli, Pianello Val Tidone, PC, EMR, Italia","category":"attractions","type":"place_of_worship","importance":0.001,"icon":"http://nominatim.openstreetmap.org/images/mapicons/place_of_worship_unknown3.p.20.png","visiting_time":30.0,"opening_hours":null,"opening_days":null,"rating":0,"photo_url":null,"description":null,"www":null},{"place_id":"50301605","geometry":{"type":"Point","coordinates":[9.322423,44.8521612]},"display_name":"Oratorio della Beata Vergine delle Grazie, Località Ossio, Molino, Romagnese, PV, LOM, Italia","category":"attractions","type":"place_of_worship","importance":0.001,"icon":"http://nominatim.openstreetmap.org/images/mapicons/place_of_worship_unknown3.p.20.png","visiting_time":30.0,"opening_hours":null,"opening_days":null,"rating":0,"photo_url":null,"description":null,"www":null},{"place_id":"49037087","geometry":{"type":"Point","coordinates":[9.3158979,44.8348291]},"display_name":"Oratorio di San Rocco, Frazione Ariore Villa, Canevizza, Romagnese, PV, LOM, Italia","category":"attractions","type":"place_of_worship","importance":0.001,"icon":"http://nominatim.openstreetmap.org/images/mapicons/place_of_worship_unknown3.p.20.png","visiting_time":30.0,"opening_hours":null,"opening_days":null,"rating":0,"photo_url":null,"description":null,"www":null},{"place_id":"150270717","geometry":{"type":"Point","coordinates":[9.327067088,44.83788045]},"display_name":"Chiesa di San Lorenzo, Piazza Castello, Canevizza, Romagnese, PV, LOM, Italia","category":"attractions","type":"place_of_worship","importance":0.001,"icon":"http://nominatim.openstreetmap.org/images/mapicons/place_of_worship_unknown3.p.20.png","visiting_time":30.0,"opening_hours":null,"opening_days":null,"rating":0,"photo_url":null,"description":null,"www":null},{"place_id":"153339363","geometry":{"type":"Point","coordinates":[9.329408653,44.8410941]},"display_name":"SPexSS412, Molino, Romagnese, PV, LOM, Italia","category":"attractions","type":"place_of_worship","importance":0.001,"icon":"http://nominatim.openstreetmap.org/images/mapicons/place_of_worship_unknown3.p.20.png","visiting_time":30.0,"opening_hours":null,"opening_days":null,"rating":0,"photo_url":null,"description":null,"www":null},{"place_id":"48954706","geometry":{"type":"Point","coordinates":[9.3456213,44.8340537]},"display_name":"Oratorio di Maria Ausiliatrice, 219 - 19, Ca' Casarini, Romagnese, PC, LOM, Italia","category":"attractions","type":"place_of_worship","importance":0.001,"icon":"http://nominatim.openstreetmap.org/images/mapicons/place_of_worship_unknown3.p.20.png","visiting_time":30.0,"opening_hours":null,"opening_days":null,"rating":0,"photo_url":null,"description":null,"www":null},{"place_id":"150471633","geometry":{"type":"Point","coordinates":[9.33245525,44.8372237]},"display_name":"Chiesetta ai Morti di San Lorenzo, SPexSS412, Canevizza, Romagnese, PV, LOM, Italia","category":"attractions","type":"place_of_worship","importance":0.001,"icon":"http://nominatim.openstreetmap.org/images/mapicons/place_of_worship_unknown3.p.20.png","visiting_time":30.0,"opening_hours":null,"opening_days":null,"rating":0,"photo_url":null,"description":null,"www":null},{"place_id":"50251535","geometry":{"type":"Point","coordinates":[9.3364492,44.8435103]},"display_name":"Oratorio di Nostra Signora di Loreto, Via Castana, Canevizza, Romagnese, PV, LOM, Italia","category":"attractions","type":"place_of_worship","importance":0.001,"icon":"http://nominatim.openstreetmap.org/images/mapicons/place_of_worship_unknown3.p.20.png","visiting_time":30.0,"opening_hours":null,"opening_days":null,"rating":0,"photo_url":null,"description":null,"www":null},{"place_id":"162463207","geometry":{"type":"Point","coordinates":[9.441318807,44.84668655]},"display_name":"SP65, C. Il Poggio, Piozzano, PC, EMR, Italia","category":"attractions","type":"place_of_worship","importance":0.001,"icon":"http://nominatim.openstreetmap.org/images/mapicons/place_of_worship_unknown3.p.20.png","visiting_time":30.0,"opening_hours":null,"opening_days":null,"rating":0,"photo_url":null,"description":null,"www":null},{"place_id":"114452371","geometry":{"type":"Point","coordinates":[9.448557616,44.90807735]},"display_name":"Chiesa di San Nazaro e Celso, SP65, C. Il Poggio, Piozzano, PC, EMR, Italia","category":"attractions","type":"place_of_worship","importance":0.001,"icon":"http://nominatim.openstreetmap.org/images/mapicons/place_of_worship_unknown3.p.20.png","visiting_time":30.0,"opening_hours":null,"opening_days":null,"rating":0,"photo_url":null,"description":null,"www":null},{"place_id":"12364434","geometry":{"type":"Point","coordinates":[9.4106243,44.905327]},"display_name":"Strada Chiarone, Ca Nuova Gazzoli, Pianello Val Tidone, PC, EMR, Italia","category":"attractions","type":"place_of_worship","importance":0.001,"icon":"http://nominatim.openstreetmap.org/images/mapicons/place_of_worship_unknown3.p.20.png","visiting_time":30.0,"opening_hours":null,"opening_days":null,"rating":0,"photo_url":null,"description":null,"www":null}]